{"users":{"Clara":{"username":"Clara","password":"123","ratedMovies":{},"reviews":{},"watchlist":[{"movieId":"insterstellarnolan2014","title":"Insterstellar","director":"Nolan","releaseYear":2014,"ratings":[6],"reviews":[],"fullTitle":"Insterstellar (2014)","userRating":"Not rated","avgRating":6.0}]},"Martin":{"username":"Martin1337","password":"123","ratedMovies":{},"reviews":{},"watchlist":[]},"Martin1337":{"username":"Martin1337","password":"123","ratedMovies":{"insterstellarnolan2014":6},"reviews":{},"watchlist":[]}},"movies":{"insterstellarnolan2014":{"movieId":"insterstellarnolan2014","title":"Insterstellar","director":"Nolan","releaseYear":2014,"ratings":[6],"reviews":[],"fullTitle":"Insterstellar (2014)","userRating":"Not rated","avgRating":6.0}},"name":"cineScore"}